savant_py_plugin_sample-0.2.13.dist-info/METADATA
savant_py_plugin_sample-0.2.13.dist-info/WHEEL
savant_py_plugin_sample.libs/libsavant_core-52b7db8f4d2d2d1b-4e7ffbe6.so
savant_py_plugin_sample.libs/libstd-ff9e2f4daa5f5044-e7b599a5.so
savant_py_plugin_sample.libs/libsavant_core_py-8f0f506d.so
savant_py_plugin_sample/__init__.py
savant_py_plugin_sample/savant_py_plugin_sample.cpython-310-aarch64-linux-gnu.so
savant_py_plugin_sample-0.2.13.dist-info/RECORD
