Metadata-Version: 2.1
Name: savant_py_plugin_sample
Version: 0.2.13
Classifier: Programming Language :: Rust
Classifier: Programming Language :: Python :: Implementation :: CPython
Classifier: Programming Language :: Python :: Implementation :: PyPy
Summary: Savant Rust core functions library
Keywords: computer-vision,video-processing
Home-Page: https://github.com/insight-platform/savant-rs
Author: Ivan Kudriavtsev <ivan.a.kudryavtsev@gmail.com>
Author-email: Ivan Kudriavtsev <ivan.a.kudryavtsev@gmail.com>
License: Apache-2.0
Requires-Python: >=3.8
Project-URL: Source Code, https://github.com/insight-platform/savant-rs
